{
  "updated": "2026-07-12T13:15:03.475843Z",
  "feeds": [
    {
      "id": "drug",
      "title": "药物 · 临床试验",
      "term": "(lecanemab OR donanemab OR \"anti-amyloid\" OR \"tau-targeting\" OR trontinemab) AND (\"clinical trial\"[Publication Type] OR phase OR efficacy)",
      "accent": "drug"
    },
    {
      "id": "mech",
      "title": "机制 · 基础研究",
      "term": "(\"Alzheimer Disease\"[Mesh]) AND (amyloid OR tau OR neuroinflammation OR APOE OR microglia) AND (mechanism OR pathology OR pathogenesis)",
      "accent": "mech"
    },
    {
      "id": "dx",
      "title": "诊断 · 生物标志物",
      "term": "(Alzheimer) AND (\"p-tau217\" OR \"plasma biomarker\" OR \"blood biomarker\" OR \"amyloid PET\" OR \"GFAP\") AND (diagnosis OR detection OR screening)",
      "accent": "dx"
    },
    {
      "id": "prev",
      "title": "预防 · 生活方式",
      "term": "(Alzheimer OR dementia) AND (prevention OR diet OR exercise OR \"cognitive reserve\" OR lifestyle OR \"physical activity\") AND (cohort OR \"risk factor\" OR longitudinal)",
      "accent": "prev"
    },
    {
      "id": "intro",
      "title": "新手村 · 入门综述",
      "term": "(\"Alzheimer Disease\"[Mesh]) AND (\"Review\"[Publication Type]) AND (overview OR introduction OR \"current understanding\" OR primer OR basics)",
      "accent": "intro",
      "style": "plain"
    }
  ],
  "items": {
    "drug": [
      {
        "pmid": "42436821",
        "title": "Statistical inference for saved time based on disease progression curves in Alzheimer's disease research.",
        "journal": "Contemporary clinical trials communicati",
        "year": "2026",
        "month": "07",
        "link": "https://pubmed.ncbi.nlm.nih.gov/42436821/",
        "zh": "提出基于疾病进展曲线上方区域计算节省时间的闭合方差公式，解决阿尔茨海默病疗效评估的统计推断难题。",
        "evidence": "OTHER"
      },
      {
        "pmid": "42434897",
        "title": "Comparative risk of amyloid-related imaging abnormalities with anti-amyloid-β monoclonal antibodies: A systematic review and penalized likelihood network meta-analysis of randomized trials.",
        "journal": "Journal of Alzheimer's disease : JAD",
        "year": "2026",
        "month": "07",
        "link": "https://pubmed.ncbi.nlm.nih.gov/42434897/",
        "zh": "抗淀粉样蛋白单抗治疗阿尔茨海默病时，ARIA-E和ARIA-H风险因药物和APOE4基因型而异。",
        "evidence": "META"
      },
      {
        "pmid": "42430964",
        "title": "Suboptimal adherence to brain health recommendations in patients pursuing anti-amyloid antibody therapy for Alzheimer's disease: Report from the Brain Health Vital Signs project.",
        "journal": "The journal of prevention of Alzheimer's",
        "year": "2026",
        "month": "07",
        "link": "https://pubmed.ncbi.nlm.nih.gov/42430964/",
        "zh": "早期阿尔茨海默病寻求抗淀粉样蛋白治疗的患者，对脑健康推荐行为的依从性普遍不足。",
        "evidence": "CASE"
      },
      {
        "pmid": "42425184",
        "title": "UPLC-ESI-qTOF-MS metabolomic characterization and in vivo neuroprotective activity of Diplotaxis harra ethanolic extract through antioxidant, anti-cholinesterase, and anti-amyloid mechanisms.",
        "journal": "Fitoterapia",
        "year": "2026",
        "month": "07",
        "link": "https://pubmed.ncbi.nlm.nih.gov/42425184/",
        "zh": "Diplotaxis harra乙醇提取物通过抗氧化、抗胆碱酯酶及抗淀粉样蛋白机制，在铝诱导的AD大鼠模型中改善认知并逆转病理。",
        "evidence": "ANIMAL"
      },
      {
        "pmid": "42423023",
        "title": "Efficacy, safety and policy implications of anti-amyloid monoclonal antibodies for Alzheimer's disease: protocol for a living systematic review and meta-analysis.",
        "journal": "BJPsych open",
        "year": "2026",
        "month": "07",
        "link": "https://pubmed.ncbi.nlm.nih.gov/42423023/",
        "zh": "抗淀粉样蛋白单克隆抗体治疗阿尔茨海默病的疗效与安全性需通过持续更新的系统评价与荟萃分析来综合评估。",
        "evidence": "META"
      },
      {
        "pmid": "42413935",
        "title": "Optimal control for anti-abeta treatment in Alzheimer's disease using a reaction-diffusion model.",
        "journal": "Journal of the Royal Society, Interface",
        "year": "2026",
        "month": "07",
        "link": "https://pubmed.ncbi.nlm.nih.gov/42413935/",
        "zh": "基于反应扩散模型的最优控制策略，可个性化优化抗Aβ治疗剂量以平衡疗效与ARIA风险。",
        "evidence": "OTHER"
      },
      {
        "pmid": "42393750",
        "title": "Microglial checkpoint collapse in Alzheimer's disease: a tri-axial framework for biomarker-informed neuroimmune therapy.",
        "journal": "Journal of neuroinflammation",
        "year": "2026",
        "month": "07",
        "link": "https://pubmed.ncbi.nlm.nih.gov/42393750/",
        "zh": "小胶质细胞检查点崩溃是阿尔茨海默病核心机制，据此提出三轴框架指导生物标志物驱动的神经免疫治疗。",
        "evidence": "REVIEW"
      },
      {
        "pmid": "42383163",
        "title": "Longitudinal biomarkers in dementia with Lewy bodies: A systematic review and meta-analysis.",
        "journal": "Clinical parkinsonism &amp; related diso",
        "year": "2026",
        "month": "07",
        "link": "https://pubmed.ncbi.nlm.nih.gov/42383163/",
        "zh": "系统综述与荟萃分析揭示，路易体痴呆的纵向生物标志物中，全脑萎缩率与临床进展显著相关。",
        "evidence": "META"
      }
    ],
    "mech": [
      {
        "pmid": "42432263",
        "title": "Repurposing apremilast for alzheimer's disease: multitarget modulation of cAMP‑PI3K/Akt-GSK‑3β and NF‑κB signaling.",
        "journal": "Metabolic brain disease",
        "year": "2026",
        "month": "07",
        "link": "https://pubmed.ncbi.nlm.nih.gov/42432263/",
        "zh": "阿普斯特通过多靶点调控cAMP-PI3K/Akt-GSK-3β和NF-κB信号通路，在阿尔茨海默病中展现治疗潜力。",
        "evidence": "REVIEW"
      },
      {
        "pmid": "42427161",
        "title": "Genetically linked brain imaging markers of memory decline in aging and Alzheimer's disease.",
        "journal": "Alzheimer's &amp; dementia : the journal",
        "year": "2026",
        "month": "07",
        "link": "https://pubmed.ncbi.nlm.nih.gov/42427161/",
        "zh": "记忆衰退与脑影像表型存在跨生命周期的遗传共变，为阿尔茨海默病早期标志物提供新线索。",
        "evidence": "COHORT"
      },
      {
        "pmid": "42427159",
        "title": "Safety considerations of gene-based therapies for Alzheimer's disease.",
        "journal": "Alzheimer's &amp; dementia : the journal",
        "year": "2026",
        "month": "07",
        "link": "https://pubmed.ncbi.nlm.nih.gov/42427159/",
        "zh": "基因疗法治疗阿尔茨海默病需重点关注中枢神经系统递送的安全性与监测参数。",
        "evidence": "REVIEW"
      },
      {
        "pmid": "42426288",
        "title": "The emerging role of circular RNAs in neurodegenerative diseases and viral infections.",
        "journal": "Journal of neurovirology",
        "year": "2026",
        "month": "07",
        "link": "https://pubmed.ncbi.nlm.nih.gov/42426288/",
        "zh": "环状RNA通过调控Aβ清除、神经炎症等核心病理，成为连接阿尔茨海默病与病毒感染的潜在新机制。",
        "evidence": "REVIEW"
      },
      {
        "pmid": "42426158",
        "title": "Attitudes of specialist memory-clinic patients with early symptomatic Alzheimer's disease towards lecanemab: results from a multicenter survey in Europe.",
        "journal": "Scientific reports",
        "year": "2026",
        "month": "07",
        "link": "https://pubmed.ncbi.nlm.nih.gov/42426158/",
        "zh": "欧洲早期AD患者对仑卡奈单抗态度积极，但担忧审批延迟及副作用。",
        "evidence": "CASE"
      },
      {
        "pmid": "42425064",
        "title": "Recent advances in Alzheimer's disease: From molecular mechanisms to therapeutic strategies.",
        "journal": "Cell",
        "year": "2026",
        "month": "07",
        "link": "https://pubmed.ncbi.nlm.nih.gov/42425064/",
        "zh": "综述揭示AD治疗从清除淀粉样斑块延缓认知衰退，转向APOE、神经免疫及生物标志物等新机制探索。",
        "evidence": "REVIEW"
      },
      {
        "pmid": "42424464",
        "title": "C1q and immunoglobulins mediate activity-dependent synapse loss in the adult brain.",
        "journal": "Science (New York, N.Y.)",
        "year": "2026",
        "month": "07",
        "link": "https://pubmed.ncbi.nlm.nih.gov/42424464/",
        "zh": "成年脑中神经元过度活跃通过C1q和免疫球蛋白介导补体依赖的突触丢失。",
        "evidence": "ANIMAL"
      },
      {
        "pmid": "42423842",
        "title": "Regulatory Effects of the PDE8B Inhibitor PF-04957325 on Cognitive Impairment and Neuroinflammation in Aβ-Induced Alzheimer's Disease Mouse Models.",
        "journal": "Neurochemical research",
        "year": "2026",
        "month": "07",
        "link": "https://pubmed.ncbi.nlm.nih.gov/42423842/",
        "zh": "PDE8B抑制剂PF-04957325通过激活cAMP/PKA/CREB通路并抑制TLR4/MyD88/NF-κB通路，改善Aβ诱导的阿尔茨海默病小鼠认知障碍和",
        "evidence": "ANIMAL"
      }
    ],
    "dx": [
      {
        "pmid": "42436578",
        "title": "A probabilistic framework for clinicopathological Alzheimer's disease using tau-PET.",
        "journal": "Alzheimer's research &amp; therapy",
        "year": "2026",
        "month": "07",
        "link": "https://pubmed.ncbi.nlm.nih.gov/42436578/",
        "zh": "基于tau-PET的贝叶斯框架可量化阿尔茨海默病临床病理概率，受年龄和淀粉样蛋白状态调节。",
        "evidence": "OTHER"
      },
      {
        "pmid": "42436533",
        "title": "Analytical and clinical validation of a novel proximity extension assay-based plasma biomarker panel in a cohort of prevalent neurodegenerative dementias.",
        "journal": "Alzheimer's research &amp; therapy",
        "year": "2026",
        "month": "07",
        "link": "https://pubmed.ncbi.nlm.nih.gov/42436533/",
        "zh": "基于PEA技术的Olink 48-plex血浆蛋白组合在多种神经退行性痴呆中展现出良好的分析性能与临床鉴别价值。",
        "evidence": "COHORT"
      },
      {
        "pmid": "42435662",
        "title": "Relative importance of blood-based biomarkers for Alzheimer's disease-specific neurodegeneration and cognitive decline.",
        "journal": "The journal of prevention of Alzheimer's",
        "year": "2026",
        "month": "07",
        "link": "https://pubmed.ncbi.nlm.nih.gov/42435662/",
        "zh": "血浆p-tau217在阿尔茨海默病特异性神经退行和认知下降中重要性最高，优于NfL、GFAP和p-tau181。",
        "evidence": "CASE"
      },
      {
        "pmid": "42434876",
        "title": "Application of plasma phosphorylated tau 217 in a memory clinic focusing on Chinese patients.",
        "journal": "Singapore medical journal",
        "year": "2026",
        "month": "07",
        "link": "https://pubmed.ncbi.nlm.nih.gov/42434876/",
        "zh": "血浆P-tau217在中国记忆门诊中可有效识别阿尔茨海默病，并确立了本地化诊断阈值。",
        "evidence": "COHORT"
      },
      {
        "pmid": "42434607",
        "title": "Comparison of a multi-analyte algorithmic immunoassay blood test with immunoprecipitation mass spectrometry for the detection of amyloid pathology.",
        "journal": "Alzheimer's &amp; dementia (Amsterdam, N",
        "year": "2026",
        "month": "07",
        "link": "https://pubmed.ncbi.nlm.nih.gov/42434607/",
        "zh": "多指标免疫算法血液检测与质谱法在检测淀粉样蛋白病理上表现相当，AUC达0.94。",
        "evidence": "COHORT"
      },
      {
        "pmid": "42427721",
        "title": "Dissociable structural and molecular pathways of age-related change in sustained attention.",
        "journal": "bioRxiv : the preprint server for biolog",
        "year": "2026",
        "month": "07",
        "link": "https://pubmed.ncbi.nlm.nih.gov/42427721/",
        "zh": "老年持续注意力下降由白质微结构退变与阿尔茨海默病理两条独立通路驱动。",
        "evidence": "COHORT"
      },
      {
        "pmid": "42422228",
        "title": "Relationships between longitudinal retinal amyloid imaging and amyloid PET in the A4 Trial.",
        "journal": "Alzheimer's &amp; dementia (Amsterdam, N",
        "year": "2026",
        "month": "07",
        "link": "https://pubmed.ncbi.nlm.nih.gov/42422228/",
        "zh": "A4试验显示，视网膜淀粉样蛋白成像与PET结果纵向关联不显著，不支持其作为替代指标。",
        "evidence": "COHORT"
      },
      {
        "pmid": "42421822",
        "title": "Identifying populations with faster cognitive decline using blood-based biomarkers.",
        "journal": "Alzheimer's &amp; dementia (New York, N.",
        "year": "2026",
        "month": "07",
        "link": "https://pubmed.ncbi.nlm.nih.gov/42421822/",
        "zh": "血液生物标志物阈值可精准识别认知衰退更快的人群，为预防试验富集策略提供依据。",
        "evidence": "COHORT"
      }
    ],
    "prev": [
      {
        "pmid": "42436541",
        "title": "Repeated mild spinal cord contusions exacerbate tauopathy development in PS19 mice.",
        "journal": "Acta neuropathologica communications",
        "year": "2026",
        "month": "07",
        "link": "https://pubmed.ncbi.nlm.nih.gov/42436541/",
        "zh": "重复轻度脊髓挫伤加剧PS19小鼠tau蛋白病进展，且不依赖急性运动功能缺损。",
        "evidence": "ANIMAL"
      },
      {
        "pmid": "42435490",
        "title": "Symptomatic conversion in a case of sporadic frontotemporal dementia: Longitudinal neuroimaging of the presymptomatic stage.",
        "journal": "Cortex; a journal devoted to the study o",
        "year": "2026",
        "month": "07",
        "link": "https://pubmed.ncbi.nlm.nih.gov/42435490/",
        "zh": "首例散发性额颞叶痴呆症前20年MRI揭示皮层萎缩先于症状出现。",
        "evidence": "CASE"
      },
      {
        "pmid": "42435422",
        "title": "Attitudes Towards Brain Health and Dementia Risk Reduction Among Minoritised Ethnic Communities in the United Kingdom: A Cross-Sectional Survey Analysis.",
        "journal": "International journal of geriatric psych",
        "year": "2026",
        "month": "07",
        "link": "https://pubmed.ncbi.nlm.nih.gov/42435422/",
        "zh": "英国少数族裔社区对脑健康和痴呆风险认知不足，且存在显著知识差距与污名化差异。",
        "evidence": "CASE"
      },
      {
        "pmid": "42434884",
        "title": "\"I have lived proudly as myself\": A Japanese woman's narrative of her life and aging.",
        "journal": "Journal of women &amp; aging",
        "year": "2026",
        "month": "07",
        "link": "https://pubmed.ncbi.nlm.nih.gov/42434884/",
        "zh": "近三十年纵向叙事研究揭示：日本老年女性在丧偶与社会变迁中，通过重构生命故事维持自我认同。",
        "evidence": "OTHER"
      },
      {
        "pmid": "42434592",
        "title": "Trajectories and timing of accelerated decline in specific memory domains preceding Alzheimer's disease.",
        "journal": "Frontiers in aging neuroscience",
        "year": "2026",
        "month": "07",
        "link": "https://pubmed.ncbi.nlm.nih.gov/42434592/",
        "zh": "阿尔茨海默病临床诊断前，特定记忆域衰退呈非线性加速且时序各异。",
        "evidence": "COHORT"
      },
      {
        "pmid": "42434375",
        "title": "A real-world feasibility study: at home longitudinal use of the Cumulus NeuLogiq® platform for electrophysiological and neurocognitive measures in patients with mild Alzheimer's Disease dementia.",
        "journal": "Frontiers in digital health",
        "year": "2026",
        "month": "07",
        "link": "https://pubmed.ncbi.nlm.nih.gov/42434375/",
        "zh": "居家纵向使用Cumulus NeuLogiq®平台可有效采集轻度AD患者的电生理及神经认知指标，支持真实世界研究。",
        "evidence": "COHORT"
      },
      {
        "pmid": "42432965",
        "title": "Association between relative fat mass and cognitive impairment in older adults: A cross-sectional study using NHANES 2011-2014 data.",
        "journal": "Medicine",
        "year": "2026",
        "month": "07",
        "link": "https://pubmed.ncbi.nlm.nih.gov/42432965/",
        "zh": "基于NHANES数据发现，相对脂肪质量（RFM）升高与美国老年人认知障碍风险显著正相关。",
        "evidence": "CASE"
      },
      {
        "pmid": "42432764",
        "title": "Activity profiles and their associations with transitions between fall and dementia: findings from a multistate time-to-event analysis.",
        "journal": "Alzheimer's research &amp; therapy",
        "year": "2026",
        "month": "07",
        "link": "https://pubmed.ncbi.nlm.nih.gov/42432764/",
        "zh": "多状态模型揭示，中年至老年人群的活动模式可预测跌倒与痴呆的发生及相互转化风险。",
        "evidence": "COHORT"
      }
    ],
    "intro": [
      {
        "pmid": "42421969",
        "title": "Osteoimmuno-brain axis: a bridge connecting osteoporosis and cognitive decline and its clinical significance in dementia and Alzheimer's disease.",
        "journal": "Frontiers in immunology",
        "year": "2026",
        "month": "07",
        "link": "https://pubmed.ncbi.nlm.nih.gov/42421969/",
        "zh": "这篇综述讲的是骨头变脆和脑子变傻可能通过免疫系统互相影响，帮普通人理解预防骨质疏松或许也能护脑。",
        "evidence": "REVIEW"
      },
      {
        "pmid": "42418295",
        "title": "Advances in the Core Role and Mechanisms of Mitochondrial Dysfunction in Alzheimer's Disease.",
        "journal": "Brain and behavior",
        "year": "2026",
        "month": "07",
        "link": "https://pubmed.ncbi.nlm.nih.gov/42418295/",
        "zh": "这篇综述讲的是大脑细胞里的能量工厂坏了会怎样加速老年痴呆，帮普通人理解保护大脑要从哪里入手。",
        "evidence": "REVIEW"
      },
      {
        "pmid": "42415281",
        "title": "Chemokines in Alzheimer's Disease: Early Defence, Late Damage and the Impact of Sex and Infection.",
        "journal": "Basic &amp; clinical pharmacology &amp; ",
        "year": "2026",
        "month": "07",
        "link": "https://pubmed.ncbi.nlm.nih.gov/42415281/",
        "zh": "这篇综述讲的是大脑里一种叫“化学信使”的小分子，在老年痴呆早期保护大脑、晚期却搞破坏，还受性别和感染影响，帮普通人理解为啥男女风险不同。",
        "evidence": "REVIEW"
      },
      {
        "pmid": "42392701",
        "title": "[Research progress on role of PINK1/Parkin-mediated mitophagy in Alzheimer's disease and TCM interventions].",
        "journal": "Zhongguo Zhong yao za zhi = Zhongguo zho",
        "year": "2026",
        "month": "07",
        "link": "https://pubmed.ncbi.nlm.nih.gov/42392701/",
        "zh": "这篇综述讲的是细胞里一种叫“自噬”的清理垃圾机制如果失灵，可能加速老年痴呆，并介绍了中药如何帮忙修复这个清理过程。",
        "evidence": "REVIEW"
      },
      {
        "pmid": "42382756",
        "title": "Calibrating microglia states in Alzheimer's disease: decoding immune-metabolic networks and nano-targeted multicomponent therapies.",
        "journal": "Frontiers in immunology",
        "year": "2026",
        "month": "07",
        "link": "https://pubmed.ncbi.nlm.nih.gov/42382756/",
        "zh": "这篇综述讲的是大脑里的清洁工细胞（小胶质细胞）如何影响老年痴呆，以及未来可能通过调整它们来改善病情，对普通人了解新疗法方向有帮助。",
        "evidence": "REVIEW"
      },
      {
        "pmid": "42381975",
        "title": "Brain Endothelial Glycocalyx as a Blood-Facing Translational Interface in Alzheimer's Disease: Beyond \"Leaky\" Barriers Toward Repair-First Stratification.",
        "journal": "Drug design, development and therapy",
        "year": "2026",
        "month": "07",
        "link": "https://pubmed.ncbi.nlm.nih.gov/42381975/",
        "zh": "这篇综述讲的是大脑血管表面一层糖膜在老年痴呆中如何受损，帮普通人理解未来可能从修复这层膜入手，而不是只盯着血管渗漏。",
        "evidence": "REVIEW"
      },
      {
        "pmid": "42363974",
        "title": "HDAC3 in Alzheimer's Disease: established evidence, unresolved questions, and translational priorities.",
        "journal": "Molecular biology reports",
        "year": "2026",
        "month": "06",
        "link": "https://pubmed.ncbi.nlm.nih.gov/42363974/",
        "zh": "这篇综述讲的是大脑里一种叫HDAC3的蛋白质可能和老年痴呆有关，但还不确定，帮你看懂目前的研究进展和未来方向。",
        "evidence": "REVIEW"
      },
      {
        "pmid": "42363707",
        "title": "Advances in 3D cell culture models for alzheimer's disease drug discovery.",
        "journal": "Expert opinion on drug discovery",
        "year": "2026",
        "month": "07",
        "link": "https://pubmed.ncbi.nlm.nih.gov/42363707/",
        "zh": "这篇综述讲的是用更逼真的立体细胞模型来测试老年痴呆药物，帮普通人更快找到有效疗法。",
        "evidence": "REVIEW"
      }
    ]
  }
}